gpam_training/__init__.py
gpam_training/binary_training.py
gpam_training/cnn_pecas_model.py
gpam_training/dataframe_preprocessing.py
gpam_training/metrics.py
gpam_training/multilabel_training.py
gpam_training/utils.py
gpam_training-0.0.16.dist-info/LICENSE
gpam_training-0.0.16.dist-info/WHEEL
gpam_training-0.0.16.dist-info/METADATA
gpam_training-0.0.16.dist-info/RECORD
